py_chanjet_utils/__init__.py
py_chanjet_utils/zkhb.py
py_chanjet_utils-1.0.4.dist-info/licenses/LICENSE
py_chanjet_utils-1.0.4.dist-info/METADATA
py_chanjet_utils-1.0.4.dist-info/WHEEL
py_chanjet_utils-1.0.4.dist-info/top_level.txt
py_chanjet_utils-1.0.4.dist-info/RECORD
