Metadata-Version: 2.4
Name: py-chanjet-utils
Version: 1.0.4
Summary: 郭磊开发的用友工具库
Home-page: https://gitee.com/guolei19850528/py_chanjet_utils
Author: guolei
Author-email: 174000902@qq.com
License: MIT
Requires-Python: >=3.0
License-File: LICENSE
Requires-Dist: beautifulsoup4
Requires-Dist: xmltodict
Requires-Dist: requests
Requires-Dist: httpx
Requires-Dist: addict
Requires-Dist: retrying
Requires-Dist: jsonschema
Requires-Dist: diskcache
Requires-Dist: redis
Requires-Dist: setuptools
Requires-Dist: wheel
Dynamic: author
Dynamic: author-email
Dynamic: description
Dynamic: description-content-type
Dynamic: home-page
Dynamic: license
Dynamic: license-file
Dynamic: requires-dist
Dynamic: requires-python
Dynamic: summary
